CHANGELOG.rst
LICENSE
MANIFEST.in
README.rst
setup.py
data/__init__.py
data/admin.py
data/fields.py
data/forms.py
data/models.py
data/tests.py
data/urls.py
data/uuid.py
data/views.py
data/migrations/0001_initial.py
data/migrations/__init__.py
data/static/.DS_Store
data/static/data/img/document.png
mohawk_data_platform.egg-info/PKG-INFO
mohawk_data_platform.egg-info/SOURCES.txt
mohawk_data_platform.egg-info/dependency_links.txt
mohawk_data_platform.egg-info/not-zip-safe
mohawk_data_platform.egg-info/requires.txt
mohawk_data_platform.egg-info/top_level.txt