Metadata-Version: 1.1
Name: mohawk-data-platform
Version: 0.9.2
Summary: A Django app for editing and publishing arbitrary JSON data in a form-based environment.
Home-page: http://github.com/mohawkhq/mohawk-data-platform
Author: Dave Hall
Author-email: dave@etianen.com
License: BSD
Platform: UNKNOWN
Classifier: Development Status :: 5 - Production/Stable
Classifier: Environment :: Web Environment
Classifier: Intended Audience :: Developers
Classifier: License :: OSI Approved :: BSD License
Classifier: Operating System :: OS Independent
Classifier: Programming Language :: Python
Classifier: Framework :: Django
